README.rst
setup.py
webtest_docgen/__init__.py
webtest_docgen/app.py
webtest_docgen/utils.py
webtest_docgen.egg-info/PKG-INFO
webtest_docgen.egg-info/SOURCES.txt
webtest_docgen.egg-info/dependency_links.txt
webtest_docgen.egg-info/not-zip-safe
webtest_docgen.egg-info/requires.txt
webtest_docgen.egg-info/top_level.txt
webtest_docgen/models/__init__.py
webtest_docgen/models/document.py
webtest_docgen/models/example.py
webtest_docgen/models/parameters.py
webtest_docgen/models/resource.py
webtest_docgen/models/root.py
webtest_docgen/providers/__init__.py
webtest_docgen/providers/base.py
webtest_docgen/providers/html.py
webtest_docgen/providers/json.py
webtest_docgen/providers/markdown.py
webtest_docgen/providers/raml.py
webtest_docgen/providers/rst.py