Metadata-Version: 1.1
Name: webtest-docgen
Version: 0.6.2
Summary: Generate RESTful API documentation from webtest tests
Home-page: http://github.com/meyt/webtest-docgen
Author: Mahdi Ghane.g
Author-email: UNKNOWN
License: GPLv3
Keywords: api_documentation api document_generator raml_client_builder
Platform: UNKNOWN
Classifier: Development Status :: 1 - Planning
Classifier: Environment :: Console
Classifier: Intended Audience :: Developers
Classifier: License :: OSI Approved :: MIT License
Classifier: Operating System :: POSIX :: Linux
Classifier: Operating System :: Unix
Classifier: Programming Language :: Python :: 3 :: Only
Classifier: Topic :: Software Development :: Documentation
Classifier: Topic :: Documentation
Classifier: Topic :: Software Development :: Build Tools
